{
  "attestation_id": "8619813f-a1d7-42e9-bb2c-bd1baa98ab1d",
  "needle_id": "d0bf7ebf-59cc-482a-ae04-52232cf1c3bb",
  "generated_at": "2025-12-23T12:22:41.623542+00:00",
  "generator": "WAVE17C_PROMOTION_DAEMON",
  "version": "1.0",
  "needle_metadata": {
    "hypothesis_title": "BTC 4H Bollinger Band Squeeze Breakout with Volume Confirmation",
    "hypothesis_category": "BREAKOUT",
    "eqs_score": 0.97,
    "sitc_confidence_level": "HIGH",
    "confluence_factor_count": 6,
    "regime_technical": "NEUTRAL",
    "regime_sovereign": "NEUTRAL",
    "defcon_level": 5,
    "created_at": "2025-12-23 13:22:31.037934+01:00"
  },
  "gate_a_criteria": {
    "eqs_threshold": 0.85,
    "sitc_required": "HIGH",
    "canonical_provenance_required": true,
    "evidence_linkage_required": true
  },
  "canonical_hash": "5a738be1a2b9b7bfc81a500a50900d0fdabddf58dd2ab4e45bca0af981066c9f",
  "vega_signature": "0236e0ccbf919139f97fc028a245b8ecfb54b8c98ced9970668601e3f9292893"
}