{
  "attestation_id": "c0757053-a41b-4d1d-9c00-b9a50e00153b",
  "needle_id": "bca1aca0-6dc6-4419-a29c-827cf64afefb",
  "generated_at": "2025-12-24T07:12:14.135902+00:00",
  "generator": "WAVE17C_PROMOTION_DAEMON",
  "version": "1.0",
  "needle_metadata": {
    "hypothesis_title": "L2 Volatility Compression Breakout - ETH/BTC Ratio Signal",
    "hypothesis_category": "TIMING",
    "eqs_score": 0.97,
    "sitc_confidence_level": "HIGH",
    "confluence_factor_count": 6,
    "regime_technical": "NEUTRAL",
    "regime_sovereign": "NEUTRAL",
    "defcon_level": 5,
    "created_at": "2025-12-24 08:11:33.254848+01:00"
  },
  "gate_a_criteria": {
    "eqs_threshold": 0.85,
    "sitc_required": "HIGH",
    "canonical_provenance_required": true,
    "evidence_linkage_required": true
  },
  "canonical_hash": "d6d2065d3de7572c503f5cc697b8981c3e045234a33ce33ef47f95258366fdbf",
  "vega_signature": "e5d7740a14397838f21f5a68797999dff16e605f823498e8bb59610a072ea0c5"
}