{
  "attestation_id": "52465057-8985-4103-bfa8-10f42654d4e9",
  "needle_id": "0b8b01cc-afcb-4f45-a66f-50b19ca815e9",
  "generated_at": "2025-12-23T07:48:34.880489+00:00",
  "generator": "WAVE17C_PROMOTION_DAEMON",
  "version": "1.0",
  "needle_metadata": {
    "hypothesis_title": "BTC Breakout Momentum After 3-Day Consolidation",
    "hypothesis_category": "MOMENTUM",
    "eqs_score": 0.97,
    "sitc_confidence_level": "HIGH",
    "confluence_factor_count": 6,
    "regime_technical": "NEUTRAL",
    "regime_sovereign": "NEUTRAL",
    "defcon_level": 5,
    "created_at": "2025-12-23 08:47:50.137990+01:00"
  },
  "gate_a_criteria": {
    "eqs_threshold": 0.85,
    "sitc_required": "HIGH",
    "canonical_provenance_required": true,
    "evidence_linkage_required": true
  },
  "canonical_hash": "b10f25e77495379172a941b3f959e7f99eb158c0f860d3c7b140107873de4d18",
  "vega_signature": "4c9f75906fda7c16777956fe7121c6733be8ea4395bc1f8050419688a3b420b2"
}