{
  "attestation_id": "b151f5e6-7004-442f-945f-3e59615fd7a2",
  "needle_id": "4424fb9f-9d23-41cc-8b93-0489d2496ee8",
  "generated_at": "2025-12-19T14:46:31.595608+00:00",
  "generator": "WAVE17C_PROMOTION_DAEMON",
  "version": "1.0",
  "needle_metadata": {
    "hypothesis_title": "BTC Volatility Compression Breakout with Volume Confirmation",
    "hypothesis_category": "BREAKOUT",
    "eqs_score": 0.97,
    "sitc_confidence_level": "HIGH",
    "confluence_factor_count": 6,
    "regime_technical": "NEUTRAL",
    "regime_sovereign": "NEUTRAL",
    "defcon_level": 5,
    "created_at": "2025-12-19 02:34:22.593573+01:00"
  },
  "gate_a_criteria": {
    "eqs_threshold": 0.85,
    "sitc_required": "HIGH",
    "canonical_provenance_required": true,
    "evidence_linkage_required": true
  },
  "canonical_hash": "768afd9fd2d109a5230e3572af241a4b24f4a1350250bd83ce18d6a26d0365f5",
  "vega_signature": "e303d8294d6bf0fb52fa165a48d1e6dbcce3a81b41fb108d3e3bf6ed2032f5d8"
}