{
  "attestation_id": "474c5669-9675-4a07-931c-cb47dc151e09",
  "needle_id": "1d6b3875-a26e-44d1-a5b9-dd30ab73d73c",
  "generated_at": "2025-12-24T20:33:37.273970+00:00",
  "generator": "WAVE17C_PROMOTION_DAEMON",
  "version": "1.0",
  "needle_metadata": {
    "hypothesis_title": "Momentum Persistence Following News-Driven Gap with Volume Confirmation",
    "hypothesis_category": "MOMENTUM",
    "eqs_score": 0.97,
    "sitc_confidence_level": "HIGH",
    "confluence_factor_count": 6,
    "regime_technical": "NEUTRAL",
    "regime_sovereign": "NEUTRAL",
    "defcon_level": 5,
    "created_at": "2025-12-24 21:33:11.232984+01:00"
  },
  "gate_a_criteria": {
    "eqs_threshold": 0.85,
    "sitc_required": "HIGH",
    "canonical_provenance_required": true,
    "evidence_linkage_required": true
  },
  "canonical_hash": "f17726e1e98a94bedefe9acf2f1934a86c1391d9662837458893cf5d126738ed",
  "vega_signature": "39027d1176e56477e26ca5c74d4d1c7b6e75aadf8c3b3302a78f63c754bd1537"
}