{
  "attestation_id": "a833034f-776e-4469-8585-c3adc7964773",
  "needle_id": "bc1281bc-347b-43c3-9f88-10b75c7fcac7",
  "generated_at": "2025-12-23T18:10:50.395439+00:00",
  "generator": "WAVE17C_PROMOTION_DAEMON",
  "version": "1.0",
  "needle_metadata": {
    "hypothesis_title": "Bull-to-Stress Transition via Volatility Compression Break",
    "hypothesis_category": "REGIME_EDGE",
    "eqs_score": 0.97,
    "sitc_confidence_level": "HIGH",
    "confluence_factor_count": 6,
    "regime_technical": "NEUTRAL",
    "regime_sovereign": "NEUTRAL",
    "defcon_level": 5,
    "created_at": "2025-12-23 19:09:57.003550+01:00"
  },
  "gate_a_criteria": {
    "eqs_threshold": 0.85,
    "sitc_required": "HIGH",
    "canonical_provenance_required": true,
    "evidence_linkage_required": true
  },
  "canonical_hash": "bf0cc0ac3a7f47872668768fd0d28e7ee74f6ff15d7ce95accad18bb4583d409",
  "vega_signature": "963e0ca412f87fd4a53bbe8ecc8ec93fc27dd9265fdb8887356975b289638750"
}