{
  "document_type": "VEGA_G3_GOLDEN_NEEDLE_EVIDENCE",
  "needle_id": "4343a19d-9bc5-4a92-826f-11694190901d",
  "classification": "G3-GOVERNANCE",
  "authority": "VEGA (Verification & Governance Authority)",
  "generated_at": "2025-12-23T01:11:29.906972+00:00",
  "directive_ref": "CEO DIRECTIVE WAVE 15/15A - AUTONOMOUS GOLDEN NEEDLE HUNT WITH SOURCE ATTRIBUTION",
  "input_provenance": {
    "price_witness": {
      "witness_id": "230cc930ae74aa08",
      "symbol": "BTCUSDT",
      "price": 88684.76,
      "source": "BINANCE",
      "timestamp": "2025-12-23T01:10:34.945664+00:00"
    },
    "regime_context": {
      "sovereign": "NEUTRAL",
      "confidence": 0.6146789090017232,
      "defcon_level": 5
    }
  },
  "source_attribution": {
    "search_query": "cryptocurrency pairs trading market",
    "retrieved_at": "2025-12-23T01:10:35.749612+00:00",
    "serper_request_id": "5a22bea8",
    "attribution_status": "COMPLETE",
    "attribution_hash": "a037db6937ce76c732ffd541d04986bf2da9c703476241bdb190e7bb3cb502f9",
    "sources": [
      {
        "source_url": "https://onlinelibrary.wiley.com/doi/full/10.1002/fut.70018",
        "source_domain": "onlinelibrary.wiley.com",
        "source_type": "OTHER",
        "published_at": "4 months ago",
        "snippet_or_excerpt": "This study examines the effectiveness of cointegrated pairs trading in cryptocurrency markets, introducing systematic parameter optimization...",
        "rank_position": 1
      },
      {
        "source_url": "https://www.nature.com/articles/s41599-025-05661-7",
        "source_domain": "www.nature.com",
        "source_type": "OTHER",
        "published_at": "2 months ago",
        "snippet_or_excerpt": "Diversification is the cornerstone of risk-adjusted portfolio construction. Yet, despite being a well-established principle in finance,...",
        "rank_position": 2
      },
      {
        "source_url": "https://www.coindesk.com/business/2025/12/19/bybit-returns-to-uk-with-100-crypto-trading-pairs-after-2-year-break",
        "source_domain": "www.coindesk.com",
        "source_type": "INSTITUTIONAL_MEDIA",
        "published_at": "3 days ago",
        "snippet_or_excerpt": "Bybit exited the U.K. in 2023 following a tightening of rules around the promotion and marketing of crypto services.",
        "rank_position": 3
      },
      {
        "source_url": "https://www.ccn.com/education/crypto/crypto-trading-pairs-guide/",
        "source_domain": "www.ccn.com",
        "source_type": "OTHER",
        "published_at": "9 months ago",
        "snippet_or_excerpt": "Discover how to choose the best crypto trading pairs, manage risk, and analyze market trends for smarter trades.",
        "rank_position": 4
      },
      {
        "source_url": "https://cryptorank.io/news/feed/b64eb-zen-usdc-trading-pair-okx",
        "source_domain": "cryptorank.io",
        "source_type": "OTHER",
        "published_at": "1 month ago",
        "snippet_or_excerpt": "BitcoinWorld ZEN/USDC Trading Pair Launch: OKX's Strategic Move Revolutionizes Crypto Trading Exciting news for cryptocurrency traders!",
        "rank_position": 5
      }
    ]
  },
  "asrp_binding": {
    "asrp_hash": "3799697422d292d1",
    "state_snapshot_timestamp": "2025-12-23T01:11:29.906972+00:00"
  },
  "sitc_chain_summary": {
    "plan_id": "c5ed7110-3761-400a-b520-ed3592610ae1",
    "confidence": "HIGH",
    "nodes_executed": 6,
    "action": "ACCEPT"
  },
  "eqs_breakdown": {
    "eqs_score": 0.97,
    "threshold": 0.85,
    "threshold_met": true,
    "confluence_factors": [
      "PRICE_TECHNICAL",
      "VOLUME_CONFIRMATION",
      "REGIME_ALIGNMENT",
      "TEMPORAL_COHERENCE",
      "SPECIFIC_TESTABLE",
      "TESTABLE_CRITERIA"
    ],
    "eqs_components": {
      "price_technical": 0.15,
      "volume_confirmation": 0.15,
      "regime_alignment": 0.15,
      "temporal_coherence": 0.15,
      "specific_testable": 0.13,
      "testable_criteria": 0.12
    }
  },
  "canonical_persistence": {
    "needle_id": "4343a19d-9bc5-4a92-826f-11694190901d",
    "canonical_hash": "f0c65b80562f9e57fce9a0ace85449d9b0b981dc9094f8fb52b6d81d14b1a39c",
    "created_at": "2025-12-23 02:11:29.904397+01:00",
    "immutability_verified": true
  },
  "hypothesis_content": {
    "title": "Stablecoin-Denominated Exchange Pair Arbitrage",
    "statement": "Price differences between USDT and USDC trading pairs for the same asset (when >0.3%) represent risk-free arbitrage opportunities that close within 30 minutes, except during STRESS regimes.",
    "category": "MEAN_REVERSION",
    "rationale": "USDT and USDC are functionally equivalent stablecoins. Large exchanges maintain automated arbitrage bots, but smaller venues or sudden liquidity events create temporary inefficiencies. This is classic arbitrage that should converge rapidly.",
    "entry_conditions": [
      "Price(Asset/USDT) vs Price(Asset/USDC) divergence > 0.3%",
      "Simultaneous long on cheap pair, short on expensive pair",
      "Regime \u2260 STRESS",
      "Liquidity > $1M on both sides of each pair",
      "Transaction costs accounted for (<0.1% per leg)"
    ],
    "exit_conditions": {
      "take_profit": "Spread closes to <0.05%",
      "stop_loss": "N/A (theoretical risk-free if executed simultaneously)",
      "time_exit": "30 minutes"
    },
    "falsification_criteria": "More than 10% of trades fail to converge within 30 minutes, or net returns after fees are negative."
  },
  "replay_pointers": {
    "hunt_session_id": "17d3c4fd-9636-462c-a3e7-4d9bf92869a4",
    "cycle_id": "EC018-WAVE15-20251223021129",
    "sitc_plan_id": "c5ed7110-3761-400a-b520-ed3592610ae1"
  },
  "cryptographic_seal": {
    "content_hash": "25d1c902e49a3ea4ecadeac8b5f8e98781911218996ead3401857d5d1662fb63",
    "algorithm": "SHA-256",
    "sealed_by": "VEGA",
    "seal_timestamp": "2025-12-23T01:11:29.906972+00:00"
  }
}