{
  "document_type": "VEGA_G3_GOLDEN_NEEDLE_EVIDENCE",
  "needle_id": "38978475-e12d-43c9-8062-2e5fa2b9042c",
  "classification": "G3-GOVERNANCE",
  "authority": "VEGA (Verification & Governance Authority)",
  "generated_at": "2025-12-18T12:36:25.522015+00:00",
  "directive_ref": "CEO DIRECTIVE WAVE 15/15A - AUTONOMOUS GOLDEN NEEDLE HUNT WITH SOURCE ATTRIBUTION",
  "input_provenance": {
    "price_witness": {
      "witness_id": "131cd4d3cf7d29ad",
      "symbol": "BTCUSDT",
      "price": 87368.0,
      "source": "BINANCE",
      "timestamp": "2025-12-18T12:35:27.507957+00:00"
    },
    "regime_context": {
      "sovereign": "NEUTRAL",
      "confidence": 0.6146789090017232,
      "defcon_level": 5
    }
  },
  "source_attribution": {
    "search_query": "cryptocurrency liquidity shift market",
    "retrieved_at": "2025-12-18T12:35:28.507115+00:00",
    "serper_request_id": "ff89b137",
    "attribution_status": "COMPLETE",
    "attribution_hash": "27cb6dcaad950b11f6789d073f07932bbd984019d34fc6d7bde585dbebb79eb1",
    "sources": [
      {
        "source_url": "https://coindcx.com/blog/crypto-deep-dives/crypto-bull-run-2025/",
        "source_domain": "coindcx.com",
        "source_type": "SOCIAL",
        "published_at": "2 days ago",
        "snippet_or_excerpt": "2025 Crypto Bull Run? Explore the buzz and expert opinions on the imminent surge. Get ready for potential opportunities in the fast-paced...",
        "rank_position": 1
      },
      {
        "source_url": "https://finance.yahoo.com/news/us-fed-ends-qt-13-095949732.html",
        "source_domain": "finance.yahoo.com",
        "source_type": "OTHER",
        "published_at": "2 weeks ago",
        "snippet_or_excerpt": "By officially putting an end to the quantitative tightening (QT) on Dec. 1, the US Federal Reserve has initiated the first steps for...",
        "rank_position": 2
      },
      {
        "source_url": "https://www.coindesk.com/markets/2025/11/15/crypto-liquidity-still-hollow-after-october-crash-risking-sharp-price-swings",
        "source_domain": "www.coindesk.com",
        "source_type": "INSTITUTIONAL_MEDIA",
        "published_at": "1 month ago",
        "snippet_or_excerpt": "Despite calmer prices after October's brutal leverage wipeout, bitcoin and ether market depth remains structurally thin, creating a more...",
        "rank_position": 3
      },
      {
        "source_url": "https://coinfomania.com/bitcoins-market-rhythm-is-shifting-as-politics-and-liquidity-take-control/",
        "source_domain": "coinfomania.com",
        "source_type": "OTHER",
        "published_at": "3 days ago",
        "snippet_or_excerpt": "Let's uncover how the Bitcoin four year cycle now tracks politics and liquidity. Are elections replacing halving events as price drivers?",
        "rank_position": 4
      },
      {
        "source_url": "https://www.ccn.com/education/crypto/bitcoin-silent-ipo-liquidity-shift-before-next-bull-run/",
        "source_domain": "www.ccn.com",
        "source_type": "OTHER",
        "published_at": "1 month ago",
        "snippet_or_excerpt": "Despite record highs in the S&P 500, tech stocks, and gold, Bitcoin remains stagnant, trading sideways even in a risk-on environment.",
        "rank_position": 5
      }
    ]
  },
  "asrp_binding": {
    "asrp_hash": "c479dea7fa599e83",
    "state_snapshot_timestamp": "2025-12-18T12:36:25.522015+00:00"
  },
  "sitc_chain_summary": {
    "plan_id": "faa62506-8c65-47ac-ae80-dc4307273ac5",
    "confidence": "HIGH",
    "nodes_executed": 6,
    "action": "ACCEPT"
  },
  "eqs_breakdown": {
    "eqs_score": 0.97,
    "threshold": 0.85,
    "threshold_met": true,
    "confluence_factors": [
      "PRICE_TECHNICAL",
      "VOLUME_CONFIRMATION",
      "REGIME_ALIGNMENT",
      "TEMPORAL_COHERENCE",
      "SPECIFIC_TESTABLE",
      "TESTABLE_CRITERIA"
    ],
    "eqs_components": {
      "price_technical": 0.15,
      "volume_confirmation": 0.15,
      "regime_alignment": 0.15,
      "temporal_coherence": 0.15,
      "specific_testable": 0.13,
      "testable_criteria": 0.12
    }
  },
  "canonical_persistence": {
    "needle_id": "38978475-e12d-43c9-8062-2e5fa2b9042c",
    "canonical_hash": "a34612d66915b0353227e2ed7b17d1902116b04a6b609efe420674ad73522e31",
    "created_at": "2025-12-18 13:36:25.516691+01:00",
    "immutability_verified": true
  },
  "hypothesis_content": {
    "title": "Stablecoin Supply Growth Divergence as Early Bull Signal",
    "statement": "When aggregate stablecoin supply (USDT+USDC) grows at >5% monthly rate while BTC price remains in neutral range (-10% to +10% over 30 days), this represents accumulation that precedes a regime shift to BULL within 20 trading days.",
    "category": "REGIME_EDGE",
    "rationale": "Stablecoin supply represents 'dry powder' waiting to deploy. Growth during price stagnation suggests accumulation. Combined with recent Fed liquidity injection, this creates potent setup for regime transition.",
    "entry_conditions": [
      "30-day stablecoin supply growth >5% (weekly confirmed)",
      "BTC price between -10% and +10% over same 30 days",
      "Crypto Fear & Greed Index <50 (neutral or fearful)"
    ],
    "exit_conditions": {
      "take_profit": "BTC enters BULL regime (price >+15% from entry)",
      "stop_loss": "Stablecoin supply growth turns negative before breakout",
      "time_exit": "20 trading days after entry if no regime shift"
    },
    "falsification_criteria": "Stablecoin supply grows but price breaks DOWN out of range, or supply growth fails to catalyze upward move within specified timeframe."
  },
  "replay_pointers": {
    "hunt_session_id": "47953ff6-b5ad-427e-9c21-1163edb2528a",
    "cycle_id": "EC018-WAVE15-20251218133625",
    "sitc_plan_id": "faa62506-8c65-47ac-ae80-dc4307273ac5"
  },
  "cryptographic_seal": {
    "content_hash": "d6316956b95c36a3dcf1fad7c16562c1f23192f94d2967399c43e13327ddaf2c",
    "algorithm": "SHA-256",
    "sealed_by": "VEGA",
    "seal_timestamp": "2025-12-18T12:36:25.522015+00:00"
  }
}