{
  "document_type": "VEGA_G3_GOLDEN_NEEDLE_EVIDENCE",
  "needle_id": "cb693cb6-809b-484d-9737-2bd69893ee08",
  "classification": "G3-GOVERNANCE",
  "authority": "VEGA (Verification & Governance Authority)",
  "generated_at": "2025-12-23T21:45:54.432281+00:00",
  "directive_ref": "CEO DIRECTIVE WAVE 15/15A - AUTONOMOUS GOLDEN NEEDLE HUNT WITH SOURCE ATTRIBUTION",
  "input_provenance": {
    "price_witness": {
      "witness_id": "221f3681eab6690b",
      "symbol": "BTCUSDT",
      "price": 87779.27,
      "source": "BINANCE",
      "timestamp": "2025-12-23T21:45:13.429554+00:00"
    },
    "regime_context": {
      "sovereign": "NEUTRAL",
      "confidence": 0.6146789090017232,
      "defcon_level": 5
    }
  },
  "source_attribution": {
    "search_query": "cryptocurrency catalyst amplification market",
    "retrieved_at": "2025-12-23T21:45:14.239949+00:00",
    "serper_request_id": "aa9aa2c0",
    "attribution_status": "COMPLETE",
    "attribution_hash": "81fa26754f48398aff7be968e7b9369638a9b8dfbba1bb525ba01ac9bea7dfd7",
    "sources": [
      {
        "source_url": "https://www.theblock.co/amp/post/383610/bitcoin-slips-as-record-28b-boxing-day-options-expiry-becomes-key-volatility-driver-analysts",
        "source_domain": "www.theblock.co",
        "source_type": "OTHER",
        "published_at": "10 hours ago",
        "snippet_or_excerpt": "Analysts warn that a record year-end options expiry is now the dominant volatility driver, as bitcoin traded under $90000 while gold surged.",
        "rank_position": 1
      },
      {
        "source_url": "https://finance.yahoo.com/news/bank-japan-hikes-rates-30-094851530.html",
        "source_domain": "finance.yahoo.com",
        "source_type": "OTHER",
        "published_at": "4 days ago",
        "snippet_or_excerpt": "The Bank of Japan raised interest rates to 0.75% on December 19, marking the highest borrowing costs in three decades and triggering...",
        "rank_position": 2
      },
      {
        "source_url": "https://ts2.tech/en/coinbase-coin-stock-week-ahead-stock-trading-rollout-prediction-market-lawsuits-analyst-targets-and-key-catalysts-for-dec-22-26-2025/",
        "source_domain": "ts2.tech",
        "source_type": "OTHER",
        "published_at": "1 day ago",
        "snippet_or_excerpt": "Coinbase (COIN) Stock Week Ahead: Stock-Trading Rollout, Prediction-Market Lawsuits, Analyst Targets and Key Catalysts for Dec.",
        "rank_position": 3
      },
      {
        "source_url": "https://www.thecoinrepublic.com/2025/12/20/bitcoin-price-braces-for-whipsaw-as-record-23b-options-expiry-threatens-2026-volatility-spike/",
        "source_domain": "www.thecoinrepublic.com",
        "source_type": "OTHER",
        "published_at": "2 days ago",
        "snippet_or_excerpt": "Bitcoin price faces record $23B options expiry Dec 26. Implied volatility at 44% signals contained year-end action before 2026 turbulence...",
        "rank_position": 4
      },
      {
        "source_url": "https://cryptorank.io/news/feed/b449f-us-inflation-surprise-as-headline-cpi-cools-to-2-7-in-november-lifts-crypto-sentiment",
        "source_domain": "cryptorank.io",
        "source_type": "OTHER",
        "published_at": "4 days ago",
        "snippet_or_excerpt": "Global markets were hit with a violent liquidity whiplash today as conflicting central bank signals collided with a massive derivatives...",
        "rank_position": 5
      }
    ]
  },
  "asrp_binding": {
    "asrp_hash": "bc0ee6c7701da441",
    "state_snapshot_timestamp": "2025-12-23T21:45:54.432281+00:00"
  },
  "sitc_chain_summary": {
    "plan_id": "2a2b7829-32bf-448a-864e-c4b2854285eb",
    "confidence": "HIGH",
    "nodes_executed": 6,
    "action": "ACCEPT"
  },
  "eqs_breakdown": {
    "eqs_score": 0.97,
    "threshold": 0.85,
    "threshold_met": true,
    "confluence_factors": [
      "PRICE_TECHNICAL",
      "VOLUME_CONFIRMATION",
      "TEMPORAL_COHERENCE",
      "CATALYST_PRESENT",
      "SPECIFIC_TESTABLE",
      "TESTABLE_CRITERIA"
    ],
    "eqs_components": {
      "price_technical": 0.15,
      "volume_confirmation": 0.15,
      "temporal_coherence": 0.15,
      "catalyst_present": 0.15,
      "specific_testable": 0.13,
      "testable_criteria": 0.12
    }
  },
  "canonical_persistence": {
    "needle_id": "cb693cb6-809b-484d-9737-2bd69893ee08",
    "canonical_hash": "4a7329a6087786de2f7ba04deec14f76167d8524daa49be0e58e25269d725b70",
    "created_at": "2025-12-23 22:45:54.428072+01:00",
    "immutability_verified": true
  },
  "hypothesis_content": {
    "title": "Coinbase Stock Catalyst \u2192 Crypto Beta Amplification",
    "statement": "Coinbase's stock-trading rollout announcement (week of Dec 22-26) will create \u22651.5x beta effect on crypto vs. traditional tech stocks, with COIN price move amplifying BTC/ETH moves in same direction over 48-hour window post-announcement.",
    "category": "MOMENTUM",
    "rationale": "Coinbase remains crypto sentiment proxy. New stock-trading product expands TAM and reinforces ecosystem dominance. Positive news should amplify crypto momentum via sentiment contagion and perceived increased adoption funnel.",
    "entry_conditions": [
      "COIN stock gaps \u22653% on news (pre-market or regular session)",
      "BTC/ETH shows initial correlation (moves same direction within 1 hour)",
      "Crypto beta to COIN exceeds 1.0 in first 2 hours post-move"
    ],
    "exit_conditions": {
      "take_profit": "Crypto achieves 1.5x COIN move (e.g., COIN +8% \u2192 BTC +12%)",
      "stop_loss": "Crypto-COIN correlation breaks (divergence >2%)",
      "time_exit": "48 hours after entry"
    },
    "falsification_criteria": "Crypto shows inverse reaction OR beta remains <0.8 to COIN move"
  },
  "replay_pointers": {
    "hunt_session_id": "511e374f-bcdb-4ac4-a1a6-d2b97fbaf509",
    "cycle_id": "EC018-WAVE15-20251223224554",
    "sitc_plan_id": "2a2b7829-32bf-448a-864e-c4b2854285eb"
  },
  "cryptographic_seal": {
    "content_hash": "88cbea934010a0e08add78434d14d0e7e7a8ce17d7f810a650bd8db6c825fcc3",
    "algorithm": "SHA-256",
    "sealed_by": "VEGA",
    "seal_timestamp": "2025-12-23T21:45:54.432281+00:00"
  }
}