{
  "metadata": {
    "test_type": "IOS012_G3_SYSTEM_LOOP",
    "module": "IoS-012",
    "gate": "G3",
    "loop_id": "49b00221-dd35-4b1e-86b5-f9ab91c15dc5",
    "session_id": "2f8d6bec-de56-4ef9-a9be-7913dbd708ce",
    "started_at": "2025-12-21T03:37:17.648468+00:00",
    "completed_at": "2025-12-21T03:37:17.741004+00:00",
    "validator": "STIG/LINE",
    "authority": "BOARD"
  },
  "timeline": {
    "regime_injection": {
      "test_id": "ff06d10e-eacb-49d6-a7a0-184f8ed06140",
      "asset_id": "SOL-USD",
      "regime": "NEUTRAL",
      "confidence": 0.7,
      "is_synthetic": false,
      "timestamp": "2025-12-21T02:13:41.311035+01:00"
    },
    "decision_computation": {
      "decision_id": "e3132fcb-a85a-4871-8558-268c9e382ff1",
      "regime": "NEUTRAL",
      "directive": "HOLD",
      "final_allocation": 0.25,
      "regime_scalar": 0.35,
      "causal_vector": 0.84,
      "skill_damper": 1.0,
      "context_hash": "58be09c42a22864f491ec31ce7c25652f81bd4d28962af1363dcf6466bf84874",
      "is_real": true
    },
    "order_execution": {
      "order_id": "HOLD_NO_ORDER",
      "order_side": "HOLD",
      "order_qty": 0.0,
      "filled_qty": 0.0,
      "filled_price": 0.0,
      "status": "HOLD",
      "submission_latency_ms": 0
    },
    "reconciliation": {
      "snapshot_id": "35439835-3d86-4c41-aee0-4782b46ed199",
      "account_value": 100000.0,
      "buying_power": 200000.0,
      "positions_count": 35,
      "divergences_count": 0,
      "timestamp": "2025-12-21T03:37:17.741004+00:00",
      "latency_ms": 19
    }
  },
  "latencies": {
    "regime_injection_ms": 72,
    "decision_computation_ms": 0,
    "execution_ms": 0,
    "reconciliation_ms": 19,
    "total_ms": 92
  },
  "sla_checks": {
    "submission_sla_ms": 150,
    "submission_sla_pass": true,
    "lifecycle_sla_ms": 1500,
    "lifecycle_sla_pass": true
  },
  "capital_preservation": {
    "preserved": true,
    "directive": "HOLD",
    "final_allocation": 0.25
  },
  "overall_status": "PASS",
  "integrity_hash": "ef6001e0c935b94c2167c7f842d59e05b4c52f28d177cad7c2a47bd54652998c"
}