{
  "metadata": {
    "test_type": "IOS012_G3_SYSTEM_LOOP",
    "module": "IoS-012",
    "gate": "G3",
    "loop_id": "b0f80a73-6870-46c0-84cd-da439e4d2b90",
    "session_id": "66efd805-fbc4-4201-87c1-50ed99705929",
    "started_at": "2026-01-29T06:19:53.755447+00:00",
    "completed_at": "2026-01-29T06:19:53.866527+00:00",
    "validator": "STIG/LINE",
    "authority": "BOARD"
  },
  "timeline": {
    "regime_injection": {
      "test_id": "a57b4211-65a1-4d4a-84ed-20e925a30820",
      "asset_id": "AAPL",
      "regime": "BEAR",
      "confidence": 0.98,
      "is_synthetic": false,
      "timestamp": "2026-01-29T04:05:48.732322+01:00"
    },
    "decision_computation": {
      "decision_id": "ddc44c40-891b-4b8c-9774-f9e5a30b3825",
      "regime": "BEAR",
      "directive": "CLOSE",
      "final_allocation": 0.0,
      "regime_scalar": 0.245,
      "causal_vector": 1.176,
      "skill_damper": 1.0,
      "context_hash": "fa67d567e42b8e0e3bedfd1ec48d088f1730d0b0fe3485f349edf82a05c8840d",
      "is_real": true
    },
    "order_execution": {
      "order_id": "HOLD_NO_ORDER",
      "order_side": "HOLD",
      "order_qty": 0.0,
      "filled_qty": 0.0,
      "filled_price": 0.0,
      "status": "HOLD",
      "submission_latency_ms": 0
    },
    "reconciliation": {
      "snapshot_id": "b329141a-5384-4400-85f1-00b8b34419c2",
      "account_value": 100000.0,
      "buying_power": 200000.0,
      "positions_count": 155,
      "divergences_count": 0,
      "timestamp": "2026-01-29T06:19:53.866527+00:00",
      "latency_ms": 10
    }
  },
  "latencies": {
    "regime_injection_ms": 101,
    "decision_computation_ms": 0,
    "execution_ms": 0,
    "reconciliation_ms": 10,
    "total_ms": 111
  },
  "sla_checks": {
    "submission_sla_ms": 150,
    "submission_sla_pass": true,
    "lifecycle_sla_ms": 1500,
    "lifecycle_sla_pass": true
  },
  "capital_preservation": {
    "preserved": true,
    "directive": "CLOSE",
    "final_allocation": 0.0
  },
  "overall_status": "PASS",
  "integrity_hash": "532269d972c0786c6b95e3382e945d27dda1c17d49c136b6cd714cd4dcf01a1a"
}