{
  "metadata": {
    "test_type": "IOS012_G3_SYSTEM_LOOP",
    "module": "IoS-012",
    "gate": "G3",
    "loop_id": "153a1fcf-dc26-4ae4-aef5-1994827a2376",
    "session_id": "60f73a40-2e6e-4bf3-81eb-db772539763e",
    "started_at": "2025-12-29T14:17:10.777008+00:00",
    "completed_at": "2025-12-29T14:17:10.920551+00:00",
    "validator": "STIG/LINE",
    "authority": "BOARD"
  },
  "timeline": {
    "regime_injection": {
      "test_id": "4e98f4c1-6ecb-43f6-9e37-0c8c917cff60",
      "asset_id": "SGO.PA",
      "regime": "NEUTRAL",
      "confidence": 0.7448,
      "is_synthetic": false,
      "timestamp": "2025-12-26T22:18:11.324945+01:00"
    },
    "decision_computation": {
      "decision_id": "febdef6b-645c-4faa-b22d-c617c412eb75",
      "regime": "NEUTRAL",
      "directive": "HOLD",
      "final_allocation": 0.25,
      "regime_scalar": 0.3724,
      "causal_vector": 0.89376,
      "skill_damper": 1.0,
      "context_hash": "96f5917598b4df9b3ed38a18d5434cf027afc01e60fbb31f55f7d99813ef0df0",
      "is_real": true
    },
    "order_execution": {
      "order_id": "HOLD_NO_ORDER",
      "order_side": "HOLD",
      "order_qty": 0.0,
      "filled_qty": 0.0,
      "filled_price": 0.0,
      "status": "HOLD",
      "submission_latency_ms": 0
    },
    "reconciliation": {
      "snapshot_id": "4f375845-1188-4cc5-beb3-1517b778a7fe",
      "account_value": 100000.0,
      "buying_power": 200000.0,
      "positions_count": 35,
      "divergences_count": 0,
      "timestamp": "2025-12-29T14:17:10.920551+00:00",
      "latency_ms": 9
    }
  },
  "latencies": {
    "regime_injection_ms": 133,
    "decision_computation_ms": 0,
    "execution_ms": 0,
    "reconciliation_ms": 9,
    "total_ms": 143
  },
  "sla_checks": {
    "submission_sla_ms": 150,
    "submission_sla_pass": true,
    "lifecycle_sla_ms": 1500,
    "lifecycle_sla_pass": true
  },
  "capital_preservation": {
    "preserved": true,
    "directive": "HOLD",
    "final_allocation": 0.25
  },
  "overall_status": "PASS",
  "integrity_hash": "80001272aa0b15fdfc505c94920916feadba70d791dd466aed91abf3992009dd"
}