{
  "batch_id": "2d12058e-d195-4399-8cb5-43b84346e321",
  "started_at": "2026-02-13T06:11:41.229302+00:00",
  "assets": {
    "BTC-USD": {
      "status": "UP_TO_DATE",
      "rows": 0
    },
    "ETH-USD": {
      "status": "UP_TO_DATE",
      "rows": 0
    },
    "SOL-USD": {
      "status": "UP_TO_DATE",
      "rows": 0
    },
    "EURUSD": {
      "status": "UP_TO_DATE",
      "rows": 0
    }
  },
  "totals": {
    "fetched": 0,
    "staged": 0,
    "canonicalized": 0
  },
  "reconciliation": {
    "decision": "REJECTED",
    "reason": "Empty batch"
  },
  "status": "SUCCESS",
  "completed_at": "2026-02-13T06:11:41.272589+00:00"
}